[
    {
        "name": "is_atype_of",
        "description": "Finds word that are more general than the given word.",
        "parameters": {
            "properties": {
                "word": {
                    "description": "Try \"hatchback\".",
                    "title": "Word",
                    "type": "string"
                }
            },
            "required": [
                "word"
            ],
            "type": "object"
        }
    },
    {
        "name": "has_types",
        "description": "Get more specific examples of types of this word.",
        "parameters": {
            "properties": {
                "word": {
                    "description": "Try \"purple\".",
                    "title": "Word",
                    "type": "string"
                }
            },
            "required": [
                "word"
            ],
            "type": "object"
        }
    },
    {
        "name": "part_of",
        "description": "The larger whole to which the word belongs.",
        "parameters": {
            "properties": {
                "word": {
                    "description": "Try \"finger\".",
                    "title": "Word",
                    "type": "string"
                }
            },
            "required": [
                "word"
            ],
            "type": "object"
        }
    },
    {
        "name": "has_parts",
        "description": "Words that are parts of the original word.",
        "parameters": {
            "properties": {
                "word": {
                    "description": "Try \"building\".",
                    "title": "Word",
                    "type": "string"
                }
            },
            "required": [
                "word"
            ],
            "type": "object"
        }
    },
    {
        "name": "is_an_instance_of",
        "description": "Words that the parameter word is an example of.",
        "parameters": {
            "properties": {
                "word": {
                    "description": "Try \"einstein\".",
                    "title": "Word",
                    "type": "string"
                }
            },
            "required": [
                "word"
            ],
            "type": "object"
        }
    },
    {
        "name": "has_instances",
        "description": "Words that are examples of the parameter word.",
        "parameters": {
            "properties": {
                "word": {
                    "description": "Try \"president\".",
                    "title": "Word",
                    "type": "string"
                }
            },
            "required": [
                "word"
            ],
            "type": "object"
        }
    },
    {
        "name": "similar_to",
        "description": "Words that similar to the original word, but are not synonyms.",
        "parameters": {
            "properties": {
                "word": {
                    "description": "Try \"bloody\".",
                    "title": "Word",
                    "type": "string"
                }
            },
            "required": [
                "word"
            ],
            "type": "object"
        }
    },
    {
        "name": "also",
        "description": "Phrases of which the word is a part.",
        "parameters": {
            "properties": {
                "word": {
                    "description": "Try \"bump\".",
                    "title": "Word",
                    "type": "string"
                }
            },
            "required": [
                "word"
            ],
            "type": "object"
        }
    },
    {
        "name": "entails",
        "description": "Words that are implied by the original word. Usually used for verbs.",
        "parameters": {
            "properties": {
                "word": {
                    "description": "Try \"rub\".",
                    "title": "Word",
                    "type": "string"
                }
            },
            "required": [
                "word"
            ],
            "type": "object"
        }
    },
    {
        "name": "member_of",
        "description": "A group to which the word belongs.",
        "parameters": {
            "properties": {
                "word": {
                    "description": "Try \"dory\".",
                    "title": "Word",
                    "type": "string"
                }
            },
            "required": [
                "word"
            ],
            "type": "object"
        }
    },
    {
        "name": "has_members",
        "description": "Words that belong to the group defined by the parameter word.",
        "parameters": {
            "properties": {
                "word": {
                    "description": "Try \"cosmos\".",
                    "title": "Word",
                    "type": "string"
                }
            },
            "required": [
                "word"
            ],
            "type": "object"
        }
    },
    {
        "name": "substance_of",
        "description": "Substances to which the original word is a part of.",
        "parameters": {
            "properties": {
                "word": {
                    "description": "",
                    "title": "Word",
                    "type": "string"
                }
            },
            "required": [
                "word"
            ],
            "type": "object"
        }
    },
    {
        "name": "has_substances",
        "description": "Words that are substances of the parameter word.",
        "parameters": {
            "properties": {
                "word": {
                    "description": "Try \"wood\".",
                    "title": "Word",
                    "type": "string"
                }
            },
            "required": [
                "word"
            ],
            "type": "object"
        }
    },
    {
        "name": "in_category",
        "description": "The domain category to which the original word belongs.",
        "parameters": {
            "properties": {
                "word": {
                    "description": "Try \"chaotic\".",
                    "title": "Word",
                    "type": "string"
                }
            },
            "required": [
                "word"
            ],
            "type": "object"
        }
    },
    {
        "name": "has_categories",
        "description": "Categories of the parameter word.",
        "parameters": {
            "properties": {
                "word": {
                    "description": "Try \"math\".",
                    "title": "Word",
                    "type": "string"
                }
            },
            "required": [
                "word"
            ],
            "type": "object"
        }
    },
    {
        "name": "usage_of",
        "description": "Words that the original word is a domain usage of.",
        "parameters": {
            "properties": {
                "word": {
                    "description": "Try \"advil\".",
                    "title": "Word",
                    "type": "string"
                }
            },
            "required": [
                "word"
            ],
            "type": "object"
        }
    },
    {
        "name": "has_usages",
        "description": "Words that are examples of the domain the original word defines.",
        "parameters": {
            "properties": {
                "word": {
                    "description": "Try \"colloquialism\".",
                    "title": "Word",
                    "type": "string"
                }
            },
            "required": [
                "word"
            ],
            "type": "object"
        }
    },
    {
        "name": "in_region",
        "description": "Geographical areas where the word is used.",
        "parameters": {
            "properties": {
                "word": {
                    "description": "Try \"chips\".",
                    "title": "Word",
                    "type": "string"
                }
            },
            "required": [
                "word"
            ],
            "type": "object"
        }
    },
    {
        "name": "region_of",
        "description": "Words used in the specified geographical area.",
        "parameters": {
            "properties": {
                "word": {
                    "description": "Try \"canada\".",
                    "title": "Word",
                    "type": "string"
                }
            },
            "required": [
                "word"
            ],
            "type": "object"
        }
    },
    {
        "name": "pertains_to",
        "description": "Words to which the original word is relevant.",
        "parameters": {
            "properties": {
                "words": {
                    "description": "Try \".22-caliber\".",
                    "title": "Words",
                    "type": "string"
                }
            },
            "required": [
                "words"
            ],
            "type": "object"
        }
    },
    {
        "name": "synonyms",
        "description": "Get synonyms of a word",
        "parameters": {
            "properties": {
                "word": {
                    "description": "Try \"lovely\".",
                    "title": "Word",
                    "type": "string"
                }
            },
            "required": [
                "word"
            ],
            "type": "object"
        }
    },
    {
        "name": "word",
        "description": "Retrieve information about a word. Results can include definitions, part of speech, synonyms, related words, syllables, and pronunciation. This method is useful to see which relationships are attached to which definition and part of speech of a word.",
        "parameters": {
            "properties": {
                "word": {
                    "description": "Try \"example\".",
                    "title": "Word",
                    "type": "string"
                }
            },
            "required": [
                "word"
            ],
            "type": "object"
        }
    },
    {
        "name": "definitions",
        "description": "Get definitions of a word, including the part of speech.",
        "parameters": {
            "properties": {
                "word": {
                    "description": "Try \"incredible\".",
                    "title": "Word",
                    "type": "string"
                }
            },
            "required": [
                "word"
            ],
            "type": "object"
        }
    },
    {
        "name": "examples",
        "description": "Get examples of how the word is used.",
        "parameters": {
            "properties": {
                "word": {
                    "description": "Try \"uneventful\".",
                    "title": "Word",
                    "type": "string"
                }
            },
            "required": [
                "word"
            ],
            "type": "object"
        }
    },
    {
        "name": "rhymes",
        "description": "Get a list of words that rhyme with the given word.",
        "parameters": {
            "properties": {
                "word": {
                    "description": "",
                    "title": "Word",
                    "type": "string"
                }
            },
            "required": [
                "word"
            ],
            "type": "object"
        }
    },
    {
        "name": "antonyms",
        "description": "Get antonyms (opposites) of a word.",
        "parameters": {
            "properties": {
                "word": {
                    "description": "Try \"free\".",
                    "title": "Word",
                    "type": "string"
                }
            },
            "required": [
                "word"
            ],
            "type": "object"
        }
    },
    {
        "name": "pronunciation",
        "description": "How to pronounce a word, according to the International Phonetic Alphabet. May include multiple results if the word is pronounced differently depending on its part of speech.",
        "parameters": {
            "properties": {
                "word": {
                    "description": "Try \"wind\". It sounds different depending on if its a noun or a verb.",
                    "title": "Word",
                    "type": "string"
                }
            },
            "required": [
                "word"
            ],
            "type": "object"
        }
    },
    {
        "name": "syllables",
        "description": "Returns the word broken down into syllables.",
        "parameters": {
            "properties": {
                "word": {
                    "description": "Try \"incredible\".",
                    "title": "Word",
                    "type": "string"
                }
            },
            "required": [
                "word"
            ],
            "type": "object"
        }
    },
    {
        "name": "frequency",
        "description": "Expands upon the frequeny score returned by the main /words/{word} endpoint. Returns zipf, a score indicating how common the word is in the English language, with a range of 1 to 7; perMillion, the number of times the word is likely to appear in a corpus of one million English words; and diversity, a 0-1 scale the shows the likelyhood of the word appearing in an English document that is part of a corpus.",
        "parameters": {
            "properties": {
                "word": {
                    "description": "Try \"apartment\"",
                    "title": "Word",
                    "type": "string"
                }
            },
            "required": [
                "word"
            ],
            "type": "object"
        }
    },
    {
        "name": "random",
        "description": "Retrieve a random word, optionally matching a search criteria. You can use the same search criteria as the \"Search\" endpoint.",
        "parameters": {
            "properties": {},
            "type": "object"
        }
    },
    {
        "name": "search",
        "description": "Search for words matching the parameters you provide. For more examples, please see the documentation on the website. https://www.wordsapi.com/docs#search",
        "parameters": {
            "properties": {
                "letterPattern": {
                    "anyOf": [
                        {
                            "type": "string"
                        },
                        {
                            "type": "null"
                        }
                    ],
                    "default": null,
                    "description": "Find words whose letters match the regular expression.",
                    "title": "Letterpattern"
                },
                "pronunciationpattern": {
                    "anyOf": [
                        {
                            "type": "string"
                        },
                        {
                            "type": "null"
                        }
                    ],
                    "default": null,
                    "description": "Find words whose pronunciation matches the regular expression.",
                    "title": "Pronunciationpattern"
                },
                "partofspeech": {
                    "anyOf": [
                        {
                            "type": "string"
                        },
                        {
                            "type": "null"
                        }
                    ],
                    "default": null,
                    "description": "The matching word must have at least one definition with this part of speech.",
                    "title": "Partofspeech"
                },
                "lettersmin": {
                    "anyOf": [
                        {
                            "type": "string"
                        },
                        {
                            "type": "null"
                        }
                    ],
                    "default": null,
                    "description": "The minimum number of letters the word must have.",
                    "title": "Lettersmin"
                },
                "letters": {
                    "anyOf": [
                        {
                            "type": "string"
                        },
                        {
                            "type": "null"
                        }
                    ],
                    "default": null,
                    "description": "The number of letters the word must have.",
                    "title": "Letters"
                },
                "lettersMax": {
                    "anyOf": [
                        {
                            "type": "string"
                        },
                        {
                            "type": "null"
                        }
                    ],
                    "default": null,
                    "description": "The maximum number of letters the word can have.",
                    "title": "Lettersmax"
                },
                "soundsmax": {
                    "anyOf": [
                        {
                            "type": "string"
                        },
                        {
                            "type": "null"
                        }
                    ],
                    "default": null,
                    "description": "The maximum number of phonemes (sounds) the word can have.",
                    "title": "Soundsmax"
                },
                "sounds": {
                    "anyOf": [
                        {
                            "type": "string"
                        },
                        {
                            "type": "null"
                        }
                    ],
                    "default": null,
                    "description": "The number of phonemes (sounds) the word mush have.",
                    "title": "Sounds"
                },
                "soundsMin": {
                    "anyOf": [
                        {
                            "type": "string"
                        },
                        {
                            "type": "null"
                        }
                    ],
                    "default": null,
                    "description": "The minimum number of phonemes (sounds) the word can have.",
                    "title": "Soundsmin"
                },
                "syllables": {
                    "anyOf": [
                        {
                            "type": "string"
                        },
                        {
                            "type": "null"
                        }
                    ],
                    "default": null,
                    "description": "The number of syllables the word must have.",
                    "title": "Syllables"
                },
                "syllablesMin": {
                    "anyOf": [
                        {
                            "type": "string"
                        },
                        {
                            "type": "null"
                        }
                    ],
                    "default": null,
                    "description": "The minimum number of syllables the word can have.",
                    "title": "Syllablesmin"
                },
                "syllablesMax": {
                    "anyOf": [
                        {
                            "type": "string"
                        },
                        {
                            "type": "null"
                        }
                    ],
                    "default": null,
                    "description": "The maximum number of syllables the word can have.",
                    "title": "Syllablesmax"
                },
                "limit": {
                    "anyOf": [
                        {
                            "type": "string"
                        },
                        {
                            "type": "null"
                        }
                    ],
                    "default": null,
                    "description": "The number of results to return per page. Must be between 1 and 100. Default is 100.",
                    "title": "Limit"
                },
                "page": {
                    "anyOf": [
                        {
                            "type": "string"
                        },
                        {
                            "type": "null"
                        }
                    ],
                    "default": null,
                    "description": "The page of results to return. The default is page 1.",
                    "title": "Page"
                },
                "frequencymin": {
                    "anyOf": [
                        {
                            "type": "string"
                        },
                        {
                            "type": "null"
                        }
                    ],
                    "default": null,
                    "description": "The minimum frequency score of words to return. You can use this to limit your search to words that people are familiar with (like \"go\", with a frequency of 6.98). The range is from 1.74 - 8.03.",
                    "title": "Frequencymin"
                },
                "frequencymax": {
                    "anyOf": [
                        {
                            "type": "string"
                        },
                        {
                            "type": "null"
                        }
                    ],
                    "default": null,
                    "description": "The maximum frequency score of words to return. You can use this to limit your search to words that aren't seen as frequently (like \"zygote\", with a frequency of 2.55). The range is from 1.74 - 8.03.",
                    "title": "Frequencymax"
                },
                "hasDetails": {
                    "anyOf": [
                        {
                            "type": "string"
                        },
                        {
                            "type": "null"
                        }
                    ],
                    "default": null,
                    "description": "A comma delimited list of detail types the word has. For instance, to find words that have both \"typeOf\" and \"hasCategories\" relationship, you would send \"hasDetails=typeOf,hasCategories\".",
                    "title": "Hasdetails"
                }
            },
            "type": "object"
        }
    }
]